crossgp/__init__.py
crossgp/baseline_sampler.py
crossgp/funcs.py
crossgp/general_sampler.py
crossgp/viscube_sampler.py
crossgp-0.1.1.dist-info/METADATA
crossgp-0.1.1.dist-info/WHEEL
crossgp-0.1.1.dist-info/RECORD
